podgenai/__init__.py
podgenai/__main__.py
podgenai/config.py
podgenai/exceptions.py
podgenai/podgenai.py
podgenai/work.py
podgenai/content/audio.py
podgenai/content/subtopics.py
podgenai/content/topic.py
podgenai/content/tts.py
podgenai/content/voice.py
podgenai/prompts/generate_subtopic.txt
podgenai/prompts/list_subtopics.txt
podgenai/prompts/list_subtopics_limit.txt
podgenai/prompts/refine_subtopic.txt
podgenai/prompts/select_voice.txt
podgenai/prompts/tts_disclaimer.txt
podgenai/util/binascii.py
podgenai/util/difflib.py
podgenai/util/dotenv_.py
podgenai/util/input.py
podgenai/util/openai.py
podgenai/util/semantic_text_splitter.py
podgenai/util/sys.py
podgenai/util/threading.py
podgenai-0.17.1.dist-info/METADATA
podgenai-0.17.1.dist-info/WHEEL
podgenai-0.17.1.dist-info/entry_points.txt
podgenai-0.17.1.dist-info/licenses/LICENSE
podgenai-0.17.1.dist-info/RECORD
