Metadata-Version: 2.3
Name: podgenai
Version: 0.17.1
Summary: OpenAI GPT based informational audiobook/podcast mp3 generator
Project-URL: Repository, https://github.com/impredicative/podgenai
Author-email: Ouroboros Chrysopoeia <impredicative@users.noreply.github.com>
Keywords: aicast,audiobook,mp3,openai,podcast
Classifier: Development Status :: 5 - Production/Stable
Classifier: License :: OSI Approved :: GNU Lesser General Public License v3 (LGPLv3)
Classifier: Natural Language :: English
Classifier: Programming Language :: Python :: 3.12
Classifier: Topic :: Multimedia :: Sound/Audio :: Speech
Requires-Python: >=3.12
Requires-Dist: click>=8.3.1
Requires-Dist: openai>=2.14.0
Requires-Dist: pathvalidate>=3.3.1
Requires-Dist: python-dotenv>=1.2.1
Requires-Dist: semantic-text-splitter<0.23.0,>=0.22.0
